test/__init__.py
test/test_access_dto.py
test/test_access_token_dto.py
test/test_access_token_request_dto.py
test/test_action_dto.py
test/test_action_started_dto.py
test/test_active_subscription_dto.py
test/test_address_dto.py
test/test_big_decimal_dto.py
test/test_body.py
test/test_body_part.py
test/test_browser_api.py
test/test_calculation_unit_dto.py
test/test_cat_tool_project_dto.py
test/test_categories_dto.py
test/test_category_dto.py
test/test_charge_dto.py
test/test_charge_language_combination_dto.py
test/test_classic_people_dto.py
test/test_classic_project_create_dto.py
test/test_client_invoices_api.py
test/test_clients_api.py
test/test_column_dto.py
test/test_common_language_combination_dto.py
test/test_competencies_dto.py
test/test_contact_dto.py
test/test_contacts_dto.py
test/test_content_disposition.py
test/test_country_dto.py
test/test_currency_dto.py
test/test_currency_exchange_rates_api.py
test/test_currency_history_dto.py
test/test_custom_field_dto.py
test/test_custom_fields_dto.py
test/test_customer_accounting_dto.py
test/test_customer_contact_emails_dto.py
test/test_customer_details_dto.py
test/test_customer_dto.py
test/test_customer_invoice_create_dto.py
test/test_customer_invoice_create_result_dto.py
test/test_customer_invoice_dates_dto.py
test/test_customer_invoice_dto.py
test/test_customer_person_dto.py
test/test_customer_responsible_persons_dto.py
test/test_customer_tax_no_dto.py
test/test_dictionaries_api.py
test/test_dictionary_entity.py
test/test_documents_dto.py
test/test_download_documents_request_dto.py
test/test_entity_with_name_dto.py
test/test_event.py
test/test_events_queue.py
test/test_export_request_dto.py
test/test_file_categorization_dto.py
test/test_file_categorizations_dto.py
test/test_file_dto.py
test/test_file_link_categorization_dto.py
test/test_file_link_categorizations_dto.py
test/test_file_share_status_dto.py
test/test_files_api.py
test/test_files_archive_dto.py
test/test_files_dto.py
test/test_files_share_status_dto.py
xtrf_api-1.0.10.dist-info/METADATA
xtrf_api-1.0.10.dist-info/WHEEL
xtrf_api-1.0.10.dist-info/top_level.txt
xtrf_api-1.0.10.dist-info/RECORD
